pypartten/__init__.py
pypartten/mediator.py
pypartten/pool.py
pypartten/proxy.py
pypartten/singleton.py
pypartten/aio/__init__.py
pypartten/aio/actor.py
pypartten/aio/pubsub.py
pypartten-0.0.2.data/data/requirements/requirements.txt
pypartten-0.0.2.data/data/requirements/requirements_dev.txt
pypartten-0.0.2.dist-info/DESCRIPTION.rst
pypartten-0.0.2.dist-info/METADATA
pypartten-0.0.2.dist-info/RECORD
pypartten-0.0.2.dist-info/WHEEL
pypartten-0.0.2.dist-info/metadata.json
pypartten-0.0.2.dist-info/top_level.txt
