Metadata-Version: 2.0
Name: pypartten
Version: 0.0.2
Summary: design patterns tools for python.
Home-page: https://github.com/Python-Tools/pypartten
Author: hsz
Author-email: hsz1273327@gmail.com
License: MIT
Keywords: tools,design patterns
Platform: UNKNOWN
Classifier: Development Status :: 3 - Alpha
Classifier: Intended Audience :: Developers
Classifier: License :: OSI Approved :: MIT License
Classifier: Programming Language :: Python :: 3.5
Classifier: Programming Language :: Python :: 3.6
Classifier: Topic :: Documentation :: Sphinx
Provides-Extra: dev
Provides-Extra: dev
Requires-Dist: coverage; extra == 'dev'
Requires-Dist: mypy; extra == 'dev'
Requires-Dist: mypy-extensions; extra == 'dev'
Requires-Dist: lxml; extra == 'dev'
Requires-Dist: wheel; extra == 'dev'
Requires-Dist: pydocstyle; extra == 'dev'
Requires-Dist: pep8; extra == 'dev'
Requires-Dist: autopep8; extra == 'dev'
